{
    "active_lock_reason": null,
    "assignee": null,
    "assignees": [],
    "author_association": "MEMBER",
    "body": "Is this expected given the ``psrose`` idiosyncrasies? For example the test ``rose_centered`` has ``-Bxa10g10 -K -Bya10g10`` but nikles annotations. ",
    "closed_at": "2022-01-22T20:00:17Z",
    "closed_by": {
        "avatar_url": "https://avatars.githubusercontent.com/u/537321?v=4",
        "events_url": "https://api.github.com/users/joa-quim/events{/privacy}",
        "followers_url": "https://api.github.com/users/joa-quim/followers",
        "following_url": "https://api.github.com/users/joa-quim/following{/other_user}",
        "gists_url": "https://api.github.com/users/joa-quim/gists{/gist_id}",
        "gravatar_id": "",
        "html_url": "https://github.com/joa-quim",
        "id": 537321,
        "login": "joa-quim",
        "node_id": "MDQ6VXNlcjUzNzMyMQ==",
        "organizations_url": "https://api.github.com/users/joa-quim/orgs",
        "received_events_url": "https://api.github.com/users/joa-quim/received_events",
        "repos_url": "https://api.github.com/users/joa-quim/repos",
        "site_admin": false,
        "starred_url": "https://api.github.com/users/joa-quim/starred{/owner}{/repo}",
        "subscriptions_url": "https://api.github.com/users/joa-quim/subscriptions",
        "type": "User",
        "url": "https://api.github.com/users/joa-quim"
    },
    "comments": 2,
    "comments_content": [
        {
            "author_association": "MEMBER",
            "body": "Expected given no -B machinery usage.  See #6141 for proposed solution.",
            "created_at": "2022-01-22T19:23:36Z",
            "html_url": "https://github.com/GenericMappingTools/gmt/issues/6251#issuecomment-1019343018",
            "id": 1019343018,
            "issue_url": "https://api.github.com/repos/GenericMappingTools/gmt/issues/6251",
            "node_id": "IC_kwDOCJzWHc48wfCq",
            "performed_via_github_app": null,
            "reactions": {
                "+1": 0,
                "-1": 0,
                "confused": 0,
                "eyes": 0,
                "heart": 0,
                "hooray": 0,
                "laugh": 0,
                "rocket": 0,
                "total_count": 0,
                "url": "https://api.github.com/repos/GenericMappingTools/gmt/issues/comments/1019343018/reactions"
            },
            "updated_at": "2022-01-22T19:23:36Z",
            "url": "https://api.github.com/repos/GenericMappingTools/gmt/issues/comments/1019343018",
            "user": {
                "avatar_url": "https://avatars.githubusercontent.com/u/26473567?v=4",
                "events_url": "https://api.github.com/users/PaulWessel/events{/privacy}",
                "followers_url": "https://api.github.com/users/PaulWessel/followers",
                "following_url": "https://api.github.com/users/PaulWessel/following{/other_user}",
                "gists_url": "https://api.github.com/users/PaulWessel/gists{/gist_id}",
                "gravatar_id": "",
                "html_url": "https://github.com/PaulWessel",
                "id": 26473567,
                "login": "PaulWessel",
                "node_id": "MDQ6VXNlcjI2NDczNTY3",
                "organizations_url": "https://api.github.com/users/PaulWessel/orgs",
                "received_events_url": "https://api.github.com/users/PaulWessel/received_events",
                "repos_url": "https://api.github.com/users/PaulWessel/repos",
                "site_admin": false,
                "starred_url": "https://api.github.com/users/PaulWessel/starred{/owner}{/repo}",
                "subscriptions_url": "https://api.github.com/users/PaulWessel/subscriptions",
                "type": "User",
                "url": "https://api.github.com/users/PaulWessel"
            }
        },
        {
            "author_association": "MEMBER",
            "body": "Ah, I remembered it but didn't remember where it was.",
            "created_at": "2022-01-22T20:00:17Z",
            "html_url": "https://github.com/GenericMappingTools/gmt/issues/6251#issuecomment-1019348586",
            "id": 1019348586,
            "issue_url": "https://api.github.com/repos/GenericMappingTools/gmt/issues/6251",
            "node_id": "IC_kwDOCJzWHc48wgZq",
            "performed_via_github_app": null,
            "reactions": {
                "+1": 0,
                "-1": 0,
                "confused": 0,
                "eyes": 0,
                "heart": 0,
                "hooray": 0,
                "laugh": 0,
                "rocket": 0,
                "total_count": 0,
                "url": "https://api.github.com/repos/GenericMappingTools/gmt/issues/comments/1019348586/reactions"
            },
            "updated_at": "2022-01-22T20:00:17Z",
            "url": "https://api.github.com/repos/GenericMappingTools/gmt/issues/comments/1019348586",
            "user": {
                "avatar_url": "https://avatars.githubusercontent.com/u/537321?v=4",
                "events_url": "https://api.github.com/users/joa-quim/events{/privacy}",
                "followers_url": "https://api.github.com/users/joa-quim/followers",
                "following_url": "https://api.github.com/users/joa-quim/following{/other_user}",
                "gists_url": "https://api.github.com/users/joa-quim/gists{/gist_id}",
                "gravatar_id": "",
                "html_url": "https://github.com/joa-quim",
                "id": 537321,
                "login": "joa-quim",
                "node_id": "MDQ6VXNlcjUzNzMyMQ==",
                "organizations_url": "https://api.github.com/users/joa-quim/orgs",
                "received_events_url": "https://api.github.com/users/joa-quim/received_events",
                "repos_url": "https://api.github.com/users/joa-quim/repos",
                "site_admin": false,
                "starred_url": "https://api.github.com/users/joa-quim/starred{/owner}{/repo}",
                "subscriptions_url": "https://api.github.com/users/joa-quim/subscriptions",
                "type": "User",
                "url": "https://api.github.com/users/joa-quim"
            }
        }
    ],
    "comments_url": "https://api.github.com/repos/GenericMappingTools/gmt/issues/6251/comments",
    "created_at": "2022-01-22T18:27:25Z",
    "events_url": "https://api.github.com/repos/GenericMappingTools/gmt/issues/6251/events",
    "html_url": "https://github.com/GenericMappingTools/gmt/issues/6251",
    "id": 1111648859,
    "labels": [
        {
            "color": "d73a4a",
            "default": true,
            "description": "Something isn't working",
            "id": 1022239695,
            "name": "bug",
            "node_id": "MDU6TGFiZWwxMDIyMjM5Njk1",
            "url": "https://api.github.com/repos/GenericMappingTools/gmt/labels/bug"
        }
    ],
    "labels_url": "https://api.github.com/repos/GenericMappingTools/gmt/issues/6251/labels{/name}",
    "locked": false,
    "milestone": null,
    "node_id": "I_kwDOCJzWHc5CQmpb",
    "number": 6251,
    "performed_via_github_app": null,
    "reactions": {
        "+1": 0,
        "-1": 0,
        "confused": 0,
        "eyes": 0,
        "heart": 0,
        "hooray": 0,
        "laugh": 0,
        "rocket": 0,
        "total_count": 0,
        "url": "https://api.github.com/repos/GenericMappingTools/gmt/issues/6251/reactions"
    },
    "repository_url": "https://api.github.com/repos/GenericMappingTools/gmt",
    "state": "closed",
    "state_reason": "completed",
    "timeline_url": "https://api.github.com/repos/GenericMappingTools/gmt/issues/6251/timeline",
    "title": "-B in psrose does not annotate",
    "updated_at": "2022-01-22T20:00:17Z",
    "url": "https://api.github.com/repos/GenericMappingTools/gmt/issues/6251",
    "user": {
        "avatar_url": "https://avatars.githubusercontent.com/u/537321?v=4",
        "events_url": "https://api.github.com/users/joa-quim/events{/privacy}",
        "followers_url": "https://api.github.com/users/joa-quim/followers",
        "following_url": "https://api.github.com/users/joa-quim/following{/other_user}",
        "gists_url": "https://api.github.com/users/joa-quim/gists{/gist_id}",
        "gravatar_id": "",
        "html_url": "https://github.com/joa-quim",
        "id": 537321,
        "login": "joa-quim",
        "node_id": "MDQ6VXNlcjUzNzMyMQ==",
        "organizations_url": "https://api.github.com/users/joa-quim/orgs",
        "received_events_url": "https://api.github.com/users/joa-quim/received_events",
        "repos_url": "https://api.github.com/users/joa-quim/repos",
        "site_admin": false,
        "starred_url": "https://api.github.com/users/joa-quim/starred{/owner}{/repo}",
        "subscriptions_url": "https://api.github.com/users/joa-quim/subscriptions",
        "type": "User",
        "url": "https://api.github.com/users/joa-quim"
    }
}